azure/schemaregistry/serializer/__init__.py
azure/schemaregistry/serializer/avroserializer/__init__.py
azure/schemaregistry/serializer/avroserializer/_abstract_avro_serializer.py
azure/schemaregistry/serializer/avroserializer/_apache_avro_serializer.py
azure/schemaregistry/serializer/avroserializer/_constants.py
azure/schemaregistry/serializer/avroserializer/_schema_registry_avro_serializer.py
azure/schemaregistry/serializer/avroserializer/_version.py
azure/schemaregistry/serializer/avroserializer/exceptions.py
azure/schemaregistry/serializer/avroserializer/aio/__init__.py
azure/schemaregistry/serializer/avroserializer/aio/_async_lru.py
azure/schemaregistry/serializer/avroserializer/aio/_schema_registry_avro_serializer_async.py
azure_schemaregistry_avroserializer-1.0.0b4.post1.dist-info/METADATA
azure_schemaregistry_avroserializer-1.0.0b4.post1.dist-info/WHEEL
azure_schemaregistry_avroserializer-1.0.0b4.post1.dist-info/top_level.txt
azure_schemaregistry_avroserializer-1.0.0b4.post1.dist-info/RECORD
