Metadata-Version: 2.1
Name: azure-schemaregistry-avroserializer
Version: 1.0.0b4.post1
Summary: Microsoft Azure Schema Registry Avro Serializer Client Library for Python
Home-page: https://github.com/Azure/azure-sdk-for-python
Author: Microsoft Corporation
Author-email: azpysdkhelp@microsoft.com
License: MIT License
Classifier: Development Status :: 7 - Inactive
Classifier: Programming Language :: Python
Classifier: Programming Language :: Python :: 2
Classifier: Programming Language :: Python :: 2.7
Classifier: Programming Language :: Python :: 3
Classifier: Programming Language :: Python :: 3.6
Classifier: Programming Language :: Python :: 3.7
Classifier: Programming Language :: Python :: 3.8
Classifier: Programming Language :: Python :: 3.9
Classifier: Programming Language :: Python :: 3.10
Classifier: License :: OSI Approved :: MIT License
Requires-Dist: azure-schemaregistry <2.0.0,>=1.0.0
Requires-Dist: avro ==1.10.0
Requires-Dist: backports.functools-lru-cache >=1.6.4 ; python_version == "2.7"
